README.rst
setup.py
dtee/__init__.py
dtee.egg-info/PKG-INFO
dtee.egg-info/SOURCES.txt
dtee.egg-info/dependency_links.txt
dtee.egg-info/requires.txt
dtee.egg-info/top_level.txt
dtee/dtee/__init__.py
dtee/dtee/dtcache.py
dtee/dtee/dtconfig.py
dtee/dtee/dtmanager.py
dtee/dtee/dtparser.py
dtee/dtee/dtparttern.py
dtee/dtee/dtrule.py
dtee/example/__init__.py
dtee/example/addon.py
dtee/example/app.py
dtee/example/config.py
dtee/example/server.py
dtee/example/tools.py
dtee/example/dtee_client/__init__.py
dtee/example/dtee_client/client.py
dtee/example/dtee_script/__init__.py
dtee/example/dtee_script/dtee_main.py
dtee/example/dtee_script/dtee_script_0119.py
dtee/example/dtee_script/dtee_script_0183.py
dtee/example/dtee_script/dtee_script_0660.py
dtee_demo/__init__.py