Metadata-Version: 1.1
Name: dtee
Version: 0.1.1
Summary: Tornado tcp stream parser
Home-page: UNKNOWN
Author: lee_shaw
Author-email: 838705177@qq.com
License: BSD License
Keywords: dtee tornado
Platform: all
Classifier: Intended Audience :: Developers
Classifier: Operating System :: OS Independent
Classifier: Natural Language :: Chinese (Simplified)
Classifier: Programming Language :: Python
Classifier: Programming Language :: Python :: 3
Classifier: Programming Language :: Python :: 3.5
Classifier: Programming Language :: Python :: 3.6
Classifier: Programming Language :: Python :: 3.7
Classifier: Programming Language :: Python :: 3.8
Classifier: Topic :: Software Development :: Libraries
